README.md
pyproject.toml
loopresources/__init__.py
loopresources.egg-info/PKG-INFO
loopresources.egg-info/SOURCES.txt
loopresources.egg-info/dependency_links.txt
loopresources.egg-info/requires.txt
loopresources.egg-info/top_level.txt
loopresources/analysis/__init__.py
loopresources/analysis/calculate_adjacency.py
loopresources/analysis/lithology_logs.py
loopresources/drillhole/__init__.py
loopresources/drillhole/dataframeinterpolator.py
loopresources/drillhole/dbconfig.py
loopresources/drillhole/desurvey.py
loopresources/drillhole/dhconfig.py
loopresources/drillhole/drillhole.py
loopresources/drillhole/drillhole_database.py
loopresources/drillhole/math.py
loopresources/drillhole/orientation.py
loopresources/drillhole/resample.py
tests/test_drillhole.py
tests/test_drillhole_database.py
tests/test_drillhole_database_comprehensive.py
tests/test_drillhole_desurvey.py
tests/test_drillhole_trace_intersection.py
tests/test_file_database.py
tests/test_from_csv.py
tests/test_lithology_logs.py
tests/test_optimized_queries.py
tests/test_preprocessing.py
tests/test_resample_intervals.py
tests/test_str_repr.py